{"preferredFilename":"transaction_training_data.csv","activityEntities":["dataSourceCreated",[{"id":"E3428B65-9A23-49F3-B70E-485A4514B88D","title":"Data Source Created","event":"dataSourceCreated","subtitle":"transaction_training_data.csv","createdDate":"2025-08-08T13:32:59Z"}],"dataSourceTrainingStarted",[{"title":"Used By","subtitle":"SmartFinance Category Classifier 1","id":"A38C470D-D863-49A4-A246-AB676DB7E247","createdDate":"2025-08-08T13:34:09Z","event":"dataSourceTrainingStarted"},{"title":"Used By","subtitle":"SmartFinance Category Classifier","id":"C0EF67CB-6D41-4D49-A7A7-87A251FE04F2","createdDate":"2025-08-08T13:44:10Z","event":"dataSourceTrainingStarted"}],"dataSourceMetrics",[{"title":"Data Summary","subtitle":"11 Classes, 260 Items","id":"EB51841B-46C9-4510-AC50-1F5C60928F20","createdDate":"2025-08-08T13:34:09Z","event":"dataSourceMetrics"},{"title":"Data Summary","subtitle":"17 Classes, 2,384 Items","id":"971D8E8C-05E1-46BC-8C3B-EFEBCAC5EA94","createdDate":"2025-08-08T13:44:10Z","event":"dataSourceMetrics"}]],"pathType":0,"dataPathRelativeToProjectURL":"..\/transaction_training_data.csv\/","version":"1.0","id":"A06AEFD9-FA44-4502-AB80-680B532DB989","title":"transaction_training_data.csv","modifiedDate":"2025-08-08T13:44:10Z","createdDate":"2025-08-08T13:32:59Z","dataURL":"file:\/\/\/Users\/snigdhatiwari\/Desktop\/transaction_training_data.csv","experimentIDs":["6F3CE067-6BAE-4941-8864-A72C82608E98"],"dataResult":{"dataSourceID":"A06AEFD9-FA44-4502-AB80-680B532DB989","classesCount":17,"createdDate":"2025-08-08T13:32:59Z","dataURL":"file:\/\/\/Users\/snigdhatiwari\/Desktop\/transaction_training_data.csv","dataAnalysis":{"objectDetectorAnalysis":{"details":{}},"issues":[{"description":"17 classes found, including Food & Dining, Transportation, Entertainment","severity":"debug"},{"description":"2384 texts found, automatically creating validation set","severity":"good"},{"description":"Smallest class is \"Subscriptions\" with 60 texts","severity":"debug"},{"description":"Largest class is \"Food & Dining\" with 306 text","severity":"debug"}],"classifierAnalysis":{"labelStats":{"Insurance":80,"Other":146,"Education":70,"Shopping":112,"Banking":127,"Entertainment":204,"Transportation":278,"Home & Garden":70,"Utilities":163,"Transfer":125,"Travel":70,"Personal Care":101,"Food & Dining":306,"Groceries":169,"Healthcare":199,"Electronics":104,"Subscriptions":60}},"summary":{"sampleCount":2384,"canUseValidation":1,"classCount":17}},"itemsCount":2384}}